ai_tool/__init__.py
ai_tool/bbox.py
ai_tool/img_slide.py
test/__init__.py
test/test.py
test/test_bbox.py
ai_tool-1.4.dist-info/LICENSE
ai_tool-1.4.dist-info/METADATA
ai_tool-1.4.dist-info/WHEEL
ai_tool-1.4.dist-info/top_level.txt
ai_tool-1.4.dist-info/RECORD
