Metadata-Version: 2.1
Name: ai-tool
Version: 1.4
Summary: compute the iou, slice picture etc.
Home-page: https://github.com/yinshunyao/ai_tools
Author: yinshunyao
Author-email: yinshunyao@qq.com
License: MIT License
Keywords: ai,tools,iou,picture slice
Platform: any
Classifier: Development Status :: 3 - Alpha
Classifier: Programming Language :: Python :: 3
Classifier: Programming Language :: Python :: 3.4
Classifier: Programming Language :: Python :: 3.5
Classifier: Programming Language :: Python :: 3.6
Classifier: Programming Language :: Python :: 3.7
Requires-Dist: numpy
Requires-Dist: opencv-python
